queryshield_sqlalchemy/__init__.py
queryshield_sqlalchemy/probe.py
queryshield_sqlalchemy/report.py
queryshield_sqlalchemy/runners/__init__.py
queryshield_sqlalchemy/runners/pytest_plugin.py
queryshield_sqlalchemy-0.2.0.dist-info/METADATA
queryshield_sqlalchemy-0.2.0.dist-info/WHEEL
queryshield_sqlalchemy-0.2.0.dist-info/RECORD
