Metadata-Version: 2.4
Name: queryshield-sqlalchemy
Version: 0.2.0
Summary: QueryShield probe for FastAPI and SQLAlchemy ORM
Project-URL: Homepage, https://queryshield.io
Project-URL: Repository, https://github.com/queryshield/queryshield
Author-email: QueryShield <dev@queryshield.io>
Requires-Python: >=3.9
Requires-Dist: queryshield-core>=0.2.0
Requires-Dist: sqlalchemy>=2.0
Provides-Extra: dev
Requires-Dist: pytest-asyncio>=0.21.0; extra == 'dev'
Requires-Dist: pytest>=7.4.0; extra == 'dev'
